{"project":"LWJGL","couplingConcept":"packages","clustering":{"tool":"infohiermap","summary":"infohiermap"},"root":{"key":"","name":"root","qualifiedName":"root","children":[{"key":"org","name":"","qualifiedName":"","children":[{"key":"lwjgl","name":"","qualifiedName":"","children":[{"key":"BufferChecks","name":"BufferChecks","qualifiedName":"org.lwjgl.BufferChecks","children":[]},{"key":"BufferUtils","name":"BufferUtils","qualifiedName":"org.lwjgl.BufferUtils","children":[]},{"key":"DefaultSysImplementation","name":"DefaultSysImplementation","qualifiedName":"org.lwjgl.DefaultSysImplementation","children":[]},{"key":"J2SESysImplementation","name":"J2SESysImplementation","qualifiedName":"org.lwjgl.J2SESysImplementation","children":[]},{"key":"LWJGLException","name":"LWJGLException","qualifiedName":"org.lwjgl.LWJGLException","children":[]},{"key":"LWJGLUtil","name":"LWJGLUtil","qualifiedName":"org.lwjgl.LWJGLUtil","children":[]},{"key":"LinuxSysImplementation","name":"LinuxSysImplementation","qualifiedName":"org.lwjgl.LinuxSysImplementation","children":[]},{"key":"MacOSXSysImplementation","name":"MacOSXSysImplementation","qualifiedName":"org.lwjgl.MacOSXSysImplementation","children":[]},{"key":"NondirectBufferWrapper","name":"NondirectBufferWrapper","qualifiedName":"org.lwjgl.NondirectBufferWrapper","children":[]},{"key":"PointerBuffer","name":"PointerBuffer","qualifiedName":"org.lwjgl.PointerBuffer","children":[]},{"key":"PointerWrapper","name":"PointerWrapper","qualifiedName":"org.lwjgl.PointerWrapper","children":[]},{"key":"PointerWrapperAbstract","name":"PointerWrapperAbstract","qualifiedName":"org.lwjgl.PointerWrapperAbstract","children":[]},{"key":"Sys","name":"Sys","qualifiedName":"org.lwjgl.Sys","children":[]},{"key":"SysImplementation","name":"SysImplementation","qualifiedName":"org.lwjgl.SysImplementation","children":[]},{"key":"WindowsSysImplementation","name":"WindowsSysImplementation","qualifiedName":"org.lwjgl.WindowsSysImplementation","children":[]},{"key":"examples","name":"","qualifiedName":"","children":[{"key":"Game","name":"Game","qualifiedName":"org.lwjgl.examples.Game","children":[]},{"key":"spaceinvaders","name":"","qualifiedName":"","children":[{"key":"AlienEntity","name":"AlienEntity","qualifiedName":"org.lwjgl.examples.spaceinvaders.AlienEntity","children":[]},{"key":"Entity","name":"Entity","qualifiedName":"org.lwjgl.examples.spaceinvaders.Entity","children":[]},{"key":"Game","name":"Game","qualifiedName":"org.lwjgl.examples.spaceinvaders.Game","children":[]},{"key":"GameApplet","name":"GameApplet","qualifiedName":"org.lwjgl.examples.spaceinvaders.GameApplet","children":[]},{"key":"ShipEntity","name":"ShipEntity","qualifiedName":"org.lwjgl.examples.spaceinvaders.ShipEntity","children":[]},{"key":"ShotEntity","name":"ShotEntity","qualifiedName":"org.lwjgl.examples.spaceinvaders.ShotEntity","children":[]},{"key":"SoundManager","name":"SoundManager","qualifiedName":"org.lwjgl.examples.spaceinvaders.SoundManager","children":[]},{"key":"Sprite","name":"Sprite","qualifiedName":"org.lwjgl.examples.spaceinvaders.Sprite","children":[]},{"key":"Texture","name":"Texture","qualifiedName":"org.lwjgl.examples.spaceinvaders.Texture","children":[]},{"key":"TextureLoader","name":"TextureLoader","qualifiedName":"org.lwjgl.examples.spaceinvaders.TextureLoader","children":[]}]}]},{"key":"input","name":"","qualifiedName":"","children":[{"key":"Controller","name":"Controller","qualifiedName":"org.lwjgl.input.Controller","children":[]},{"key":"ControllerEvent","name":"ControllerEvent","qualifiedName":"org.lwjgl.input.ControllerEvent","children":[]},{"key":"Controllers","name":"Controllers","qualifiedName":"org.lwjgl.input.Controllers","children":[]},{"key":"Cursor","name":"Cursor","qualifiedName":"org.lwjgl.input.Cursor","children":[]},{"key":"JInputController","name":"JInputController","qualifiedName":"org.lwjgl.input.JInputController","children":[]},{"key":"Keyboard","name":"Keyboard","qualifiedName":"org.lwjgl.input.Keyboard","children":[]},{"key":"Mouse","name":"Mouse","qualifiedName":"org.lwjgl.input.Mouse","children":[]},{"key":"OpenGLPackageAccess","name":"OpenGLPackageAccess","qualifiedName":"org.lwjgl.input.OpenGLPackageAccess","children":[]}]},{"key":"openal","name":"","qualifiedName":"","children":[{"key":"AL","name":"AL","qualifiedName":"org.lwjgl.openal.AL","children":[]},{"key":"AL10","name":"AL10","qualifiedName":"org.lwjgl.openal.AL10","children":[]},{"key":"AL11","name":"AL11","qualifiedName":"org.lwjgl.openal.AL11","children":[]},{"key":"ALC10","name":"ALC10","qualifiedName":"org.lwjgl.openal.ALC10","children":[]},{"key":"ALC11","name":"ALC11","qualifiedName":"org.lwjgl.openal.ALC11","children":[]},{"key":"ALCcontext","name":"ALCcontext","qualifiedName":"org.lwjgl.openal.ALCcontext","children":[]},{"key":"ALCdevice","name":"ALCdevice","qualifiedName":"org.lwjgl.openal.ALCdevice","children":[]},{"key":"EFX10","name":"EFX10","qualifiedName":"org.lwjgl.openal.EFX10","children":[]},{"key":"EFXUtil","name":"EFXUtil","qualifiedName":"org.lwjgl.openal.EFXUtil","children":[]},{"key":"OpenALException","name":"OpenALException","qualifiedName":"org.lwjgl.openal.OpenALException","children":[]},{"key":"Util","name":"Util","qualifiedName":"org.lwjgl.openal.Util","children":[]}]},{"key":"opencl","name":"","qualifiedName":"","children":[{"key":"AMDDeviceAttributeQuery","name":"AMDDeviceAttributeQuery","qualifiedName":"org.lwjgl.opencl.AMDDeviceAttributeQuery","children":[]},{"key":"APIUtil","name":"APIUtil","qualifiedName":"org.lwjgl.opencl.APIUtil","children":[]},{"key":"APPLEContextLoggingFunctions","name":"APPLEContextLoggingFunctions","qualifiedName":"org.lwjgl.opencl.APPLEContextLoggingFunctions","children":[]},{"key":"APPLEContextLoggingUtil","name":"APPLEContextLoggingUtil","qualifiedName":"org.lwjgl.opencl.APPLEContextLoggingUtil","children":[]},{"key":"APPLEGLSharing","name":"APPLEGLSharing","qualifiedName":"org.lwjgl.opencl.APPLEGLSharing","children":[]},{"key":"APPLESetMemObjectDestructor","name":"APPLESetMemObjectDestructor","qualifiedName":"org.lwjgl.opencl.APPLESetMemObjectDestructor","children":[]},{"key":"CL","name":"CL","qualifiedName":"org.lwjgl.opencl.CL","children":[]},{"key":"CL10","name":"CL10","qualifiedName":"org.lwjgl.opencl.CL10","children":[]},{"key":"CL10GL","name":"CL10GL","qualifiedName":"org.lwjgl.opencl.CL10GL","children":[]},{"key":"CL11","name":"CL11","qualifiedName":"org.lwjgl.opencl.CL11","children":[]},{"key":"CLBuildProgramCallback","name":"CLBuildProgramCallback","qualifiedName":"org.lwjgl.opencl.CLBuildProgramCallback","children":[]},{"key":"CLCallback","name":"CLCallback","qualifiedName":"org.lwjgl.opencl.CLCallback","children":[]},{"key":"CLCapabilities","name":"CLCapabilities","qualifiedName":"org.lwjgl.opencl.CLCapabilities","children":[]},{"key":"CLChecks","name":"CLChecks","qualifiedName":"org.lwjgl.opencl.CLChecks","children":[]},{"key":"CLCommandQueue","name":"CLCommandQueue","qualifiedName":"org.lwjgl.opencl.CLCommandQueue","children":[]},{"key":"CLContext","name":"CLContext","qualifiedName":"org.lwjgl.opencl.CLContext","children":[]},{"key":"CLContextCallback","name":"CLContextCallback","qualifiedName":"org.lwjgl.opencl.CLContextCallback","children":[]},{"key":"CLDevice","name":"CLDevice","qualifiedName":"org.lwjgl.opencl.CLDevice","children":[]},{"key":"CLDeviceCapabilities","name":"CLDeviceCapabilities","qualifiedName":"org.lwjgl.opencl.CLDeviceCapabilities","children":[]},{"key":"CLEvent","name":"CLEvent","qualifiedName":"org.lwjgl.opencl.CLEvent","children":[]},{"key":"CLEventCallback","name":"CLEventCallback","qualifiedName":"org.lwjgl.opencl.CLEventCallback","children":[]},{"key":"CLFunctionAddress","name":"CLFunctionAddress","qualifiedName":"org.lwjgl.opencl.CLFunctionAddress","children":[]},{"key":"CLKernel","name":"CLKernel","qualifiedName":"org.lwjgl.opencl.CLKernel","children":[]},{"key":"CLMem","name":"CLMem","qualifiedName":"org.lwjgl.opencl.CLMem","children":[]},{"key":"CLMemObjectDestructorCallback","name":"CLMemObjectDestructorCallback","qualifiedName":"org.lwjgl.opencl.CLMemObjectDestructorCallback","children":[]},{"key":"CLNativeKernel","name":"CLNativeKernel","qualifiedName":"org.lwjgl.opencl.CLNativeKernel","children":[]},{"key":"CLObject","name":"CLObject","qualifiedName":"org.lwjgl.opencl.CLObject","children":[]},{"key":"CLObjectChild","name":"CLObjectChild","qualifiedName":"org.lwjgl.opencl.CLObjectChild","children":[]},{"key":"CLObjectRegistry","name":"CLObjectRegistry","qualifiedName":"org.lwjgl.opencl.CLObjectRegistry","children":[]},{"key":"CLObjectRegistryGlobal","name":"CLObjectRegistryGlobal","qualifiedName":"org.lwjgl.opencl.CLObjectRegistryGlobal","children":[]},{"key":"CLObjectRetainable","name":"CLObjectRetainable","qualifiedName":"org.lwjgl.opencl.CLObjectRetainable","children":[]},{"key":"CLPlatform","name":"CLPlatform","qualifiedName":"org.lwjgl.opencl.CLPlatform","children":[]},{"key":"CLPlatformCapabilities","name":"CLPlatformCapabilities","qualifiedName":"org.lwjgl.opencl.CLPlatformCapabilities","children":[]},{"key":"CLProgram","name":"CLProgram","qualifiedName":"org.lwjgl.opencl.CLProgram","children":[]},{"key":"CLSampler","name":"CLSampler","qualifiedName":"org.lwjgl.opencl.CLSampler","children":[]},{"key":"CallbackUtil","name":"CallbackUtil","qualifiedName":"org.lwjgl.opencl.CallbackUtil","children":[]},{"key":"EXTDeviceFission","name":"EXTDeviceFission","qualifiedName":"org.lwjgl.opencl.EXTDeviceFission","children":[]},{"key":"EXTMigrateMemobject","name":"EXTMigrateMemobject","qualifiedName":"org.lwjgl.opencl.EXTMigrateMemobject","children":[]},{"key":"FastLongMap","name":"FastLongMap","qualifiedName":"org.lwjgl.opencl.FastLongMap","children":[]},{"key":"InfoUtil","name":"InfoUtil","qualifiedName":"org.lwjgl.opencl.InfoUtil","children":[]},{"key":"InfoUtilAbstract","name":"InfoUtilAbstract","qualifiedName":"org.lwjgl.opencl.InfoUtilAbstract","children":[]},{"key":"InfoUtilFactory","name":"InfoUtilFactory","qualifiedName":"org.lwjgl.opencl.InfoUtilFactory","children":[]},{"key":"KHRFp16","name":"KHRFp16","qualifiedName":"org.lwjgl.opencl.KHRFp16","children":[]},{"key":"KHRFp64","name":"KHRFp64","qualifiedName":"org.lwjgl.opencl.KHRFp64","children":[]},{"key":"KHRGLEvent","name":"KHRGLEvent","qualifiedName":"org.lwjgl.opencl.KHRGLEvent","children":[]},{"key":"KHRGLSharing","name":"KHRGLSharing","qualifiedName":"org.lwjgl.opencl.KHRGLSharing","children":[]},{"key":"KHRICD","name":"KHRICD","qualifiedName":"org.lwjgl.opencl.KHRICD","children":[]},{"key":"NVDeviceAttributeQuery","name":"NVDeviceAttributeQuery","qualifiedName":"org.lwjgl.opencl.NVDeviceAttributeQuery","children":[]},{"key":"OpenCLException","name":"OpenCLException","qualifiedName":"org.lwjgl.opencl.OpenCLException","children":[]},{"key":"Util","name":"Util","qualifiedName":"org.lwjgl.opencl.Util","children":[]},{"key":"api","name":"","qualifiedName":"","children":[{"key":"CLBufferRegion","name":"CLBufferRegion","qualifiedName":"org.lwjgl.opencl.api.CLBufferRegion","children":[]},{"key":"CLImageFormat","name":"CLImageFormat","qualifiedName":"org.lwjgl.opencl.api.CLImageFormat","children":[]},{"key":"Filter","name":"Filter","qualifiedName":"org.lwjgl.opencl.api.Filter","children":[]}]}]},{"key":"opengl","name":"","qualifiedName":"","children":[{"key":"AMDDebugOutput","name":"AMDDebugOutput","qualifiedName":"org.lwjgl.opengl.AMDDebugOutput","children":[]},{"key":"AMDDebugOutputCallback","name":"AMDDebugOutputCallback","qualifiedName":"org.lwjgl.opengl.AMDDebugOutputCallback","children":[]},{"key":"AMDDepthClampSeparate","name":"AMDDepthClampSeparate","qualifiedName":"org.lwjgl.opengl.AMDDepthClampSeparate","children":[]},{"key":"AMDDrawBuffersBlend","name":"AMDDrawBuffersBlend","qualifiedName":"org.lwjgl.opengl.AMDDrawBuffersBlend","children":[]},{"key":"AMDNameGenDelete","name":"AMDNameGenDelete","qualifiedName":"org.lwjgl.opengl.AMDNameGenDelete","children":[]},{"key":"AMDPerformanceMonitor","name":"AMDPerformanceMonitor","qualifiedName":"org.lwjgl.opengl.AMDPerformanceMonitor","children":[]},{"key":"AMDSeamlessCubemapPerTexture","name":"AMDSeamlessCubemapPerTexture","qualifiedName":"org.lwjgl.opengl.AMDSeamlessCubemapPerTexture","children":[]},{"key":"AMDVertexShaderTessellator","name":"AMDVertexShaderTessellator","qualifiedName":"org.lwjgl.opengl.AMDVertexShaderTessellator","children":[]},{"key":"APIUtil","name":"APIUtil","qualifiedName":"org.lwjgl.opengl.APIUtil","children":[]},{"key":"APPLEAuxDepthStencil","name":"APPLEAuxDepthStencil","qualifiedName":"org.lwjgl.opengl.APPLEAuxDepthStencil","children":[]},{"key":"APPLEClientStorage","name":"APPLEClientStorage","qualifiedName":"org.lwjgl.opengl.APPLEClientStorage","children":[]},{"key":"APPLEElementArray","name":"APPLEElementArray","qualifiedName":"org.lwjgl.opengl.APPLEElementArray","children":[]},{"key":"APPLEFence","name":"APPLEFence","qualifiedName":"org.lwjgl.opengl.APPLEFence","children":[]},{"key":"APPLEFloatPixels","name":"APPLEFloatPixels","qualifiedName":"org.lwjgl.opengl.APPLEFloatPixels","children":[]},{"key":"APPLEFlushBufferRange","name":"APPLEFlushBufferRange","qualifiedName":"org.lwjgl.opengl.APPLEFlushBufferRange","children":[]},{"key":"APPLEObjectPurgeable","name":"APPLEObjectPurgeable","qualifiedName":"org.lwjgl.opengl.APPLEObjectPurgeable","children":[]},{"key":"APPLEPackedPixels","name":"APPLEPackedPixels","qualifiedName":"org.lwjgl.opengl.APPLEPackedPixels","children":[]},{"key":"APPLERgb422","name":"APPLERgb422","qualifiedName":"org.lwjgl.opengl.APPLERgb422","children":[]},{"key":"APPLERowBytes","name":"APPLERowBytes","qualifiedName":"org.lwjgl.opengl.APPLERowBytes","children":[]},{"key":"APPLETextureRange","name":"APPLETextureRange","qualifiedName":"org.lwjgl.opengl.APPLETextureRange","children":[]},{"key":"APPLEVertexArrayObject","name":"APPLEVertexArrayObject","qualifiedName":"org.lwjgl.opengl.APPLEVertexArrayObject","children":[]},{"key":"APPLEVertexArrayRange","name":"APPLEVertexArrayRange","qualifiedName":"org.lwjgl.opengl.APPLEVertexArrayRange","children":[]},{"key":"APPLEVertexProgramEvaluators","name":"APPLEVertexProgramEvaluators","qualifiedName":"org.lwjgl.opengl.APPLEVertexProgramEvaluators","children":[]},{"key":"APPLEYcbcr422","name":"APPLEYcbcr422","qualifiedName":"org.lwjgl.opengl.APPLEYcbcr422","children":[]},{"key":"ARBBlendFuncExtended","name":"ARBBlendFuncExtended","qualifiedName":"org.lwjgl.opengl.ARBBlendFuncExtended","children":[]},{"key":"ARBBufferObject","name":"ARBBufferObject","qualifiedName":"org.lwjgl.opengl.ARBBufferObject","children":[]},{"key":"ARBCLEvent","name":"ARBCLEvent","qualifiedName":"org.lwjgl.opengl.ARBCLEvent","children":[]},{"key":"ARBColorBufferFloat","name":"ARBColorBufferFloat","qualifiedName":"org.lwjgl.opengl.ARBColorBufferFloat","children":[]},{"key":"ARBCopyBuffer","name":"ARBCopyBuffer","qualifiedName":"org.lwjgl.opengl.ARBCopyBuffer","children":[]},{"key":"ARBDebugOutput","name":"ARBDebugOutput","qualifiedName":"org.lwjgl.opengl.ARBDebugOutput","children":[]},{"key":"ARBDebugOutputCallback","name":"ARBDebugOutputCallback","qualifiedName":"org.lwjgl.opengl.ARBDebugOutputCallback","children":[]},{"key":"ARBDepthBufferFloat","name":"ARBDepthBufferFloat","qualifiedName":"org.lwjgl.opengl.ARBDepthBufferFloat","children":[]},{"key":"ARBDepthClamp","name":"ARBDepthClamp","qualifiedName":"org.lwjgl.opengl.ARBDepthClamp","children":[]},{"key":"ARBDepthTexture","name":"ARBDepthTexture","qualifiedName":"org.lwjgl.opengl.ARBDepthTexture","children":[]},{"key":"ARBDrawBuffers","name":"ARBDrawBuffers","qualifiedName":"org.lwjgl.opengl.ARBDrawBuffers","children":[]},{"key":"ARBDrawBuffersBlend","name":"ARBDrawBuffersBlend","qualifiedName":"org.lwjgl.opengl.ARBDrawBuffersBlend","children":[]},{"key":"ARBDrawElementsBaseVertex","name":"ARBDrawElementsBaseVertex","qualifiedName":"org.lwjgl.opengl.ARBDrawElementsBaseVertex","children":[]},{"key":"ARBDrawIndirect","name":"ARBDrawIndirect","qualifiedName":"org.lwjgl.opengl.ARBDrawIndirect","children":[]},{"key":"ARBDrawInstanced","name":"ARBDrawInstanced","qualifiedName":"org.lwjgl.opengl.ARBDrawInstanced","children":[]},{"key":"ARBES2Compatibility","name":"ARBES2Compatibility","qualifiedName":"org.lwjgl.opengl.ARBES2Compatibility","children":[]},{"key":"ARBFragmentProgram","name":"ARBFragmentProgram","qualifiedName":"org.lwjgl.opengl.ARBFragmentProgram","children":[]},{"key":"ARBFragmentShader","name":"ARBFragmentShader","qualifiedName":"org.lwjgl.opengl.ARBFragmentShader","children":[]},{"key":"ARBFramebufferObject","name":"ARBFramebufferObject","qualifiedName":"org.lwjgl.opengl.ARBFramebufferObject","children":[]},{"key":"ARBFramebufferSRGB","name":"ARBFramebufferSRGB","qualifiedName":"org.lwjgl.opengl.ARBFramebufferSRGB","children":[]},{"key":"ARBGeometryShader4","name":"ARBGeometryShader4","qualifiedName":"org.lwjgl.opengl.ARBGeometryShader4","children":[]},{"key":"ARBGetProgramBinary","name":"ARBGetProgramBinary","qualifiedName":"org.lwjgl.opengl.ARBGetProgramBinary","children":[]},{"key":"ARBGpuShader5","name":"ARBGpuShader5","qualifiedName":"org.lwjgl.opengl.ARBGpuShader5","children":[]},{"key":"ARBGpuShaderFp64","name":"ARBGpuShaderFp64","qualifiedName":"org.lwjgl.opengl.ARBGpuShaderFp64","children":[]},{"key":"ARBHalfFloatPixel","name":"ARBHalfFloatPixel","qualifiedName":"org.lwjgl.opengl.ARBHalfFloatPixel","children":[]},{"key":"ARBHalfFloatVertex","name":"ARBHalfFloatVertex","qualifiedName":"org.lwjgl.opengl.ARBHalfFloatVertex","children":[]},{"key":"ARBImaging","name":"ARBImaging","qualifiedName":"org.lwjgl.opengl.ARBImaging","children":[]},{"key":"ARBInstancedArrays","name":"ARBInstancedArrays","qualifiedName":"org.lwjgl.opengl.ARBInstancedArrays","children":[]},{"key":"ARBMapBufferRange","name":"ARBMapBufferRange","qualifiedName":"org.lwjgl.opengl.ARBMapBufferRange","children":[]},{"key":"ARBMatrixPalette","name":"ARBMatrixPalette","qualifiedName":"org.lwjgl.opengl.ARBMatrixPalette","children":[]},{"key":"ARBMultisample","name":"ARBMultisample","qualifiedName":"org.lwjgl.opengl.ARBMultisample","children":[]},{"key":"ARBMultitexture","name":"ARBMultitexture","qualifiedName":"org.lwjgl.opengl.ARBMultitexture","children":[]},{"key":"ARBOcclusionQuery","name":"ARBOcclusionQuery","qualifiedName":"org.lwjgl.opengl.ARBOcclusionQuery","children":[]},{"key":"ARBOcclusionQuery2","name":"ARBOcclusionQuery2","qualifiedName":"org.lwjgl.opengl.ARBOcclusionQuery2","children":[]},{"key":"ARBPixelBufferObject","name":"ARBPixelBufferObject","qualifiedName":"org.lwjgl.opengl.ARBPixelBufferObject","children":[]},{"key":"ARBPointParameters","name":"ARBPointParameters","qualifiedName":"org.lwjgl.opengl.ARBPointParameters","children":[]},{"key":"ARBPointSprite","name":"ARBPointSprite","qualifiedName":"org.lwjgl.opengl.ARBPointSprite","children":[]},{"key":"ARBProgram","name":"ARBProgram","qualifiedName":"org.lwjgl.opengl.ARBProgram","children":[]},{"key":"ARBProvokingVertex","name":"ARBProvokingVertex","qualifiedName":"org.lwjgl.opengl.ARBProvokingVertex","children":[]},{"key":"ARBRobustness","name":"ARBRobustness","qualifiedName":"org.lwjgl.opengl.ARBRobustness","children":[]},{"key":"ARBSampleShading","name":"ARBSampleShading","qualifiedName":"org.lwjgl.opengl.ARBSampleShading","children":[]},{"key":"ARBSamplerObjects","name":"ARBSamplerObjects","qualifiedName":"org.lwjgl.opengl.ARBSamplerObjects","children":[]},{"key":"ARBSeamlessCubeMap","name":"ARBSeamlessCubeMap","qualifiedName":"org.lwjgl.opengl.ARBSeamlessCubeMap","children":[]},{"key":"ARBSeparateShaderObjects","name":"ARBSeparateShaderObjects","qualifiedName":"org.lwjgl.opengl.ARBSeparateShaderObjects","children":[]},{"key":"ARBShaderObjects","name":"ARBShaderObjects","qualifiedName":"org.lwjgl.opengl.ARBShaderObjects","children":[]},{"key":"ARBShaderSubroutine","name":"ARBShaderSubroutine","qualifiedName":"org.lwjgl.opengl.ARBShaderSubroutine","children":[]},{"key":"ARBShadingLanguage100","name":"ARBShadingLanguage100","qualifiedName":"org.lwjgl.opengl.ARBShadingLanguage100","children":[]},{"key":"ARBShadingLanguageInclude","name":"ARBShadingLanguageInclude","qualifiedName":"org.lwjgl.opengl.ARBShadingLanguageInclude","children":[]},{"key":"ARBShadow","name":"ARBShadow","qualifiedName":"org.lwjgl.opengl.ARBShadow","children":[]},{"key":"ARBShadowAmbient","name":"ARBShadowAmbient","qualifiedName":"org.lwjgl.opengl.ARBShadowAmbient","children":[]},{"key":"ARBSync","name":"ARBSync","qualifiedName":"org.lwjgl.opengl.ARBSync","children":[]},{"key":"ARBTessellationShader","name":"ARBTessellationShader","qualifiedName":"org.lwjgl.opengl.ARBTessellationShader","children":[]},{"key":"ARBTextureBorderClamp","name":"ARBTextureBorderClamp","qualifiedName":"org.lwjgl.opengl.ARBTextureBorderClamp","children":[]},{"key":"ARBTextureBufferObject","name":"ARBTextureBufferObject","qualifiedName":"org.lwjgl.opengl.ARBTextureBufferObject","children":[]},{"key":"ARBTextureCompression","name":"ARBTextureCompression","qualifiedName":"org.lwjgl.opengl.ARBTextureCompression","children":[]},{"key":"ARBTextureCompressionBPTC","name":"ARBTextureCompressionBPTC","qualifiedName":"org.lwjgl.opengl.ARBTextureCompressionBPTC","children":[]},{"key":"ARBTextureCompressionRGTC","name":"ARBTextureCompressionRGTC","qualifiedName":"org.lwjgl.opengl.ARBTextureCompressionRGTC","children":[]},{"key":"ARBTextureCubeMap","name":"ARBTextureCubeMap","qualifiedName":"org.lwjgl.opengl.ARBTextureCubeMap","children":[]},{"key":"ARBTextureCubeMapArray","name":"ARBTextureCubeMapArray","qualifiedName":"org.lwjgl.opengl.ARBTextureCubeMapArray","children":[]},{"key":"ARBTextureEnvCombine","name":"ARBTextureEnvCombine","qualifiedName":"org.lwjgl.opengl.ARBTextureEnvCombine","children":[]},{"key":"ARBTextureEnvDot3","name":"ARBTextureEnvDot3","qualifiedName":"org.lwjgl.opengl.ARBTextureEnvDot3","children":[]},{"key":"ARBTextureFloat","name":"ARBTextureFloat","qualifiedName":"org.lwjgl.opengl.ARBTextureFloat","children":[]},{"key":"ARBTextureGather","name":"ARBTextureGather","qualifiedName":"org.lwjgl.opengl.ARBTextureGather","children":[]},{"key":"ARBTextureMirroredRepeat","name":"ARBTextureMirroredRepeat","qualifiedName":"org.lwjgl.opengl.ARBTextureMirroredRepeat","children":[]},{"key":"ARBTextureMultisample","name":"ARBTextureMultisample","qualifiedName":"org.lwjgl.opengl.ARBTextureMultisample","children":[]},{"key":"ARBTextureRGB10_A2UI","name":"ARBTextureRGB10_A2UI","qualifiedName":"org.lwjgl.opengl.ARBTextureRGB10_A2UI","children":[]},{"key":"ARBTextureRectangle","name":"ARBTextureRectangle","qualifiedName":"org.lwjgl.opengl.ARBTextureRectangle","children":[]},{"key":"ARBTextureRg","name":"ARBTextureRg","qualifiedName":"org.lwjgl.opengl.ARBTextureRg","children":[]},{"key":"ARBTextureSwizzle","name":"ARBTextureSwizzle","qualifiedName":"org.lwjgl.opengl.ARBTextureSwizzle","children":[]},{"key":"ARBTimerQuery","name":"ARBTimerQuery","qualifiedName":"org.lwjgl.opengl.ARBTimerQuery","children":[]},{"key":"ARBTransformFeedback2","name":"ARBTransformFeedback2","qualifiedName":"org.lwjgl.opengl.ARBTransformFeedback2","children":[]},{"key":"ARBTransformFeedback3","name":"ARBTransformFeedback3","qualifiedName":"org.lwjgl.opengl.ARBTransformFeedback3","children":[]},{"key":"ARBTransposeMatrix","name":"ARBTransposeMatrix","qualifiedName":"org.lwjgl.opengl.ARBTransposeMatrix","children":[]},{"key":"ARBUniformBufferObject","name":"ARBUniformBufferObject","qualifiedName":"org.lwjgl.opengl.ARBUniformBufferObject","children":[]},{"key":"ARBVertexArrayBgra","name":"ARBVertexArrayBgra","qualifiedName":"org.lwjgl.opengl.ARBVertexArrayBgra","children":[]},{"key":"ARBVertexArrayObject","name":"ARBVertexArrayObject","qualifiedName":"org.lwjgl.opengl.ARBVertexArrayObject","children":[]},{"key":"ARBVertexAttrib64bit","name":"ARBVertexAttrib64bit","qualifiedName":"org.lwjgl.opengl.ARBVertexAttrib64bit","children":[]},{"key":"ARBVertexBlend","name":"ARBVertexBlend","qualifiedName":"org.lwjgl.opengl.ARBVertexBlend","children":[]},{"key":"ARBVertexBufferObject","name":"ARBVertexBufferObject","qualifiedName":"org.lwjgl.opengl.ARBVertexBufferObject","children":[]},{"key":"ARBVertexProgram","name":"ARBVertexProgram","qualifiedName":"org.lwjgl.opengl.ARBVertexProgram","children":[]},{"key":"ARBVertexShader","name":"ARBVertexShader","qualifiedName":"org.lwjgl.opengl.ARBVertexShader","children":[]},{"key":"ARBVertexType2_10_10_10_REV","name":"ARBVertexType2_10_10_10_REV","qualifiedName":"org.lwjgl.opengl.ARBVertexType2_10_10_10_REV","children":[]},{"key":"ARBViewportArray","name":"ARBViewportArray","qualifiedName":"org.lwjgl.opengl.ARBViewportArray","children":[]},{"key":"ARBWindowPos","name":"ARBWindowPos","qualifiedName":"org.lwjgl.opengl.ARBWindowPos","children":[]},{"key":"ATIDrawBuffers","name":"ATIDrawBuffers","qualifiedName":"org.lwjgl.opengl.ATIDrawBuffers","children":[]},{"key":"ATIElementArray","name":"ATIElementArray","qualifiedName":"org.lwjgl.opengl.ATIElementArray","children":[]},{"key":"ATIEnvmapBumpmap","name":"ATIEnvmapBumpmap","qualifiedName":"org.lwjgl.opengl.ATIEnvmapBumpmap","children":[]},{"key":"ATIFragmentShader","name":"ATIFragmentShader","qualifiedName":"org.lwjgl.opengl.ATIFragmentShader","children":[]},{"key":"ATIMapObjectBuffer","name":"ATIMapObjectBuffer","qualifiedName":"org.lwjgl.opengl.ATIMapObjectBuffer","children":[]},{"key":"ATIMeminfo","name":"ATIMeminfo","qualifiedName":"org.lwjgl.opengl.ATIMeminfo","children":[]},{"key":"ATIPnTriangles","name":"ATIPnTriangles","qualifiedName":"org.lwjgl.opengl.ATIPnTriangles","children":[]},{"key":"ATISeparateStencil","name":"ATISeparateStencil","qualifiedName":"org.lwjgl.opengl.ATISeparateStencil","children":[]},{"key":"ATITextFragmentShader","name":"ATITextFragmentShader","qualifiedName":"org.lwjgl.opengl.ATITextFragmentShader","children":[]},{"key":"ATITextureCompression3DC","name":"ATITextureCompression3DC","qualifiedName":"org.lwjgl.opengl.ATITextureCompression3DC","children":[]},{"key":"ATITextureEnvCombine3","name":"ATITextureEnvCombine3","qualifiedName":"org.lwjgl.opengl.ATITextureEnvCombine3","children":[]},{"key":"ATITextureFloat","name":"ATITextureFloat","qualifiedName":"org.lwjgl.opengl.ATITextureFloat","children":[]},{"key":"ATITextureMirrorOnce","name":"ATITextureMirrorOnce","qualifiedName":"org.lwjgl.opengl.ATITextureMirrorOnce","children":[]},{"key":"ATIVertexArrayObject","name":"ATIVertexArrayObject","qualifiedName":"org.lwjgl.opengl.ATIVertexArrayObject","children":[]},{"key":"ATIVertexAttribArrayObject","name":"ATIVertexAttribArrayObject","qualifiedName":"org.lwjgl.opengl.ATIVertexAttribArrayObject","children":[]},{"key":"ATIVertexStreams","name":"ATIVertexStreams","qualifiedName":"org.lwjgl.opengl.ATIVertexStreams","children":[]},{"key":"AWTCanvasImplementation","name":"AWTCanvasImplementation","qualifiedName":"org.lwjgl.opengl.AWTCanvasImplementation","children":[]},{"key":"AWTGLCanvas","name":"AWTGLCanvas","qualifiedName":"org.lwjgl.opengl.AWTGLCanvas","children":[]},{"key":"AWTSurfaceLock","name":"AWTSurfaceLock","qualifiedName":"org.lwjgl.opengl.AWTSurfaceLock","children":[]},{"key":"AWTUtil","name":"AWTUtil","qualifiedName":"org.lwjgl.opengl.AWTUtil","children":[]},{"key":"AbstractDrawable","name":"AbstractDrawable","qualifiedName":"org.lwjgl.opengl.AbstractDrawable","children":[]},{"key":"BaseReferences","name":"BaseReferences","qualifiedName":"org.lwjgl.opengl.BaseReferences","children":[]},{"key":"CallbackUtil","name":"CallbackUtil","qualifiedName":"org.lwjgl.opengl.CallbackUtil","children":[]},{"key":"Context","name":"Context","qualifiedName":"org.lwjgl.opengl.Context","children":[]},{"key":"ContextAttribs","name":"ContextAttribs","qualifiedName":"org.lwjgl.opengl.ContextAttribs","children":[]},{"key":"ContextAttribsImplementation","name":"ContextAttribsImplementation","qualifiedName":"org.lwjgl.opengl.ContextAttribsImplementation","children":[]},{"key":"ContextCapabilities","name":"ContextCapabilities","qualifiedName":"org.lwjgl.opengl.ContextCapabilities","children":[]},{"key":"ContextImplementation","name":"ContextImplementation","qualifiedName":"org.lwjgl.opengl.ContextImplementation","children":[]},{"key":"Display","name":"Display","qualifiedName":"org.lwjgl.opengl.Display","children":[]},{"key":"DisplayImplementation","name":"DisplayImplementation","qualifiedName":"org.lwjgl.opengl.DisplayImplementation","children":[]},{"key":"DisplayMode","name":"DisplayMode","qualifiedName":"org.lwjgl.opengl.DisplayMode","children":[]},{"key":"Drawable","name":"Drawable","qualifiedName":"org.lwjgl.opengl.Drawable","children":[]},{"key":"DrawableLWJGL","name":"DrawableLWJGL","qualifiedName":"org.lwjgl.opengl.DrawableLWJGL","children":[]},{"key":"EXTAbgr","name":"EXTAbgr","qualifiedName":"org.lwjgl.opengl.EXTAbgr","children":[]},{"key":"EXTBgra","name":"EXTBgra","qualifiedName":"org.lwjgl.opengl.EXTBgra","children":[]},{"key":"EXTBindableUniform","name":"EXTBindableUniform","qualifiedName":"org.lwjgl.opengl.EXTBindableUniform","children":[]},{"key":"EXTBlendColor","name":"EXTBlendColor","qualifiedName":"org.lwjgl.opengl.EXTBlendColor","children":[]},{"key":"EXTBlendEquationSeparate","name":"EXTBlendEquationSeparate","qualifiedName":"org.lwjgl.opengl.EXTBlendEquationSeparate","children":[]},{"key":"EXTBlendFuncSeparate","name":"EXTBlendFuncSeparate","qualifiedName":"org.lwjgl.opengl.EXTBlendFuncSeparate","children":[]},{"key":"EXTBlendMinmax","name":"EXTBlendMinmax","qualifiedName":"org.lwjgl.opengl.EXTBlendMinmax","children":[]},{"key":"EXTBlendSubtract","name":"EXTBlendSubtract","qualifiedName":"org.lwjgl.opengl.EXTBlendSubtract","children":[]},{"key":"EXTCgShader","name":"EXTCgShader","qualifiedName":"org.lwjgl.opengl.EXTCgShader","children":[]},{"key":"EXTCompiledVertexArray","name":"EXTCompiledVertexArray","qualifiedName":"org.lwjgl.opengl.EXTCompiledVertexArray","children":[]},{"key":"EXTDepthBoundsTest","name":"EXTDepthBoundsTest","qualifiedName":"org.lwjgl.opengl.EXTDepthBoundsTest","children":[]},{"key":"EXTDirectStateAccess","name":"EXTDirectStateAccess","qualifiedName":"org.lwjgl.opengl.EXTDirectStateAccess","children":[]},{"key":"EXTDrawBuffers2","name":"EXTDrawBuffers2","qualifiedName":"org.lwjgl.opengl.EXTDrawBuffers2","children":[]},{"key":"EXTDrawInstanced","name":"EXTDrawInstanced","qualifiedName":"org.lwjgl.opengl.EXTDrawInstanced","children":[]},{"key":"EXTDrawRangeElements","name":"EXTDrawRangeElements","qualifiedName":"org.lwjgl.opengl.EXTDrawRangeElements","children":[]},{"key":"EXTFogCoord","name":"EXTFogCoord","qualifiedName":"org.lwjgl.opengl.EXTFogCoord","children":[]},{"key":"EXTFramebufferBlit","name":"EXTFramebufferBlit","qualifiedName":"org.lwjgl.opengl.EXTFramebufferBlit","children":[]},{"key":"EXTFramebufferMultisample","name":"EXTFramebufferMultisample","qualifiedName":"org.lwjgl.opengl.EXTFramebufferMultisample","children":[]},{"key":"EXTFramebufferObject","name":"EXTFramebufferObject","qualifiedName":"org.lwjgl.opengl.EXTFramebufferObject","children":[]},{"key":"EXTFramebufferSRGB","name":"EXTFramebufferSRGB","qualifiedName":"org.lwjgl.opengl.EXTFramebufferSRGB","children":[]},{"key":"EXTGeometryShader4","name":"EXTGeometryShader4","qualifiedName":"org.lwjgl.opengl.EXTGeometryShader4","children":[]},{"key":"EXTGpuProgramParameters","name":"EXTGpuProgramParameters","qualifiedName":"org.lwjgl.opengl.EXTGpuProgramParameters","children":[]},{"key":"EXTGpuShader4","name":"EXTGpuShader4","qualifiedName":"org.lwjgl.opengl.EXTGpuShader4","children":[]},{"key":"EXTMultiDrawArrays","name":"EXTMultiDrawArrays","qualifiedName":"org.lwjgl.opengl.EXTMultiDrawArrays","children":[]},{"key":"EXTPackedDepthStencil","name":"EXTPackedDepthStencil","qualifiedName":"org.lwjgl.opengl.EXTPackedDepthStencil","children":[]},{"key":"EXTPackedFloat","name":"EXTPackedFloat","qualifiedName":"org.lwjgl.opengl.EXTPackedFloat","children":[]},{"key":"EXTPackedPixels","name":"EXTPackedPixels","qualifiedName":"org.lwjgl.opengl.EXTPackedPixels","children":[]},{"key":"EXTPalettedTexture","name":"EXTPalettedTexture","qualifiedName":"org.lwjgl.opengl.EXTPalettedTexture","children":[]},{"key":"EXTPixelBufferObject","name":"EXTPixelBufferObject","qualifiedName":"org.lwjgl.opengl.EXTPixelBufferObject","children":[]},{"key":"EXTPointParameters","name":"EXTPointParameters","qualifiedName":"org.lwjgl.opengl.EXTPointParameters","children":[]},{"key":"EXTProvokingVertex","name":"EXTProvokingVertex","qualifiedName":"org.lwjgl.opengl.EXTProvokingVertex","children":[]},{"key":"EXTRescaleNormal","name":"EXTRescaleNormal","qualifiedName":"org.lwjgl.opengl.EXTRescaleNormal","children":[]},{"key":"EXTSecondaryColor","name":"EXTSecondaryColor","qualifiedName":"org.lwjgl.opengl.EXTSecondaryColor","children":[]},{"key":"EXTSeparateShaderObjects","name":"EXTSeparateShaderObjects","qualifiedName":"org.lwjgl.opengl.EXTSeparateShaderObjects","children":[]},{"key":"EXTSeparateSpecularColor","name":"EXTSeparateSpecularColor","qualifiedName":"org.lwjgl.opengl.EXTSeparateSpecularColor","children":[]},{"key":"EXTShaderImageLoadStore","name":"EXTShaderImageLoadStore","qualifiedName":"org.lwjgl.opengl.EXTShaderImageLoadStore","children":[]},{"key":"EXTSharedTexturePalette","name":"EXTSharedTexturePalette","qualifiedName":"org.lwjgl.opengl.EXTSharedTexturePalette","children":[]},{"key":"EXTStencilClearTag","name":"EXTStencilClearTag","qualifiedName":"org.lwjgl.opengl.EXTStencilClearTag","children":[]},{"key":"EXTStencilTwoSide","name":"EXTStencilTwoSide","qualifiedName":"org.lwjgl.opengl.EXTStencilTwoSide","children":[]},{"key":"EXTStencilWrap","name":"EXTStencilWrap","qualifiedName":"org.lwjgl.opengl.EXTStencilWrap","children":[]},{"key":"EXTTextureArray","name":"EXTTextureArray","qualifiedName":"org.lwjgl.opengl.EXTTextureArray","children":[]},{"key":"EXTTextureBufferObject","name":"EXTTextureBufferObject","qualifiedName":"org.lwjgl.opengl.EXTTextureBufferObject","children":[]},{"key":"EXTTextureCompressionLATC","name":"EXTTextureCompressionLATC","qualifiedName":"org.lwjgl.opengl.EXTTextureCompressionLATC","children":[]},{"key":"EXTTextureCompressionRGTC","name":"EXTTextureCompressionRGTC","qualifiedName":"org.lwjgl.opengl.EXTTextureCompressionRGTC","children":[]},{"key":"EXTTextureCompressionS3TC","name":"EXTTextureCompressionS3TC","qualifiedName":"org.lwjgl.opengl.EXTTextureCompressionS3TC","children":[]},{"key":"EXTTextureEnvCombine","name":"EXTTextureEnvCombine","qualifiedName":"org.lwjgl.opengl.EXTTextureEnvCombine","children":[]},{"key":"EXTTextureEnvDot3","name":"EXTTextureEnvDot3","qualifiedName":"org.lwjgl.opengl.EXTTextureEnvDot3","children":[]},{"key":"EXTTextureFilterAnisotropic","name":"EXTTextureFilterAnisotropic","qualifiedName":"org.lwjgl.opengl.EXTTextureFilterAnisotropic","children":[]},{"key":"EXTTextureInteger","name":"EXTTextureInteger","qualifiedName":"org.lwjgl.opengl.EXTTextureInteger","children":[]},{"key":"EXTTextureLODBias","name":"EXTTextureLODBias","qualifiedName":"org.lwjgl.opengl.EXTTextureLODBias","children":[]},{"key":"EXTTextureMirrorClamp","name":"EXTTextureMirrorClamp","qualifiedName":"org.lwjgl.opengl.EXTTextureMirrorClamp","children":[]},{"key":"EXTTextureRectangle","name":"EXTTextureRectangle","qualifiedName":"org.lwjgl.opengl.EXTTextureRectangle","children":[]},{"key":"EXTTextureSRGB","name":"EXTTextureSRGB","qualifiedName":"org.lwjgl.opengl.EXTTextureSRGB","children":[]},{"key":"EXTTextureSRGBDecode","name":"EXTTextureSRGBDecode","qualifiedName":"org.lwjgl.opengl.EXTTextureSRGBDecode","children":[]},{"key":"EXTTextureSharedExponent","name":"EXTTextureSharedExponent","qualifiedName":"org.lwjgl.opengl.EXTTextureSharedExponent","children":[]},{"key":"EXTTextureSnorm","name":"EXTTextureSnorm","qualifiedName":"org.lwjgl.opengl.EXTTextureSnorm","children":[]},{"key":"EXTTextureSwizzle","name":"EXTTextureSwizzle","qualifiedName":"org.lwjgl.opengl.EXTTextureSwizzle","children":[]},{"key":"EXTTimerQuery","name":"EXTTimerQuery","qualifiedName":"org.lwjgl.opengl.EXTTimerQuery","children":[]},{"key":"EXTTransformFeedback","name":"EXTTransformFeedback","qualifiedName":"org.lwjgl.opengl.EXTTransformFeedback","children":[]},{"key":"EXTVertexArrayBgra","name":"EXTVertexArrayBgra","qualifiedName":"org.lwjgl.opengl.EXTVertexArrayBgra","children":[]},{"key":"EXTVertexAttrib64bit","name":"EXTVertexAttrib64bit","qualifiedName":"org.lwjgl.opengl.EXTVertexAttrib64bit","children":[]},{"key":"EXTVertexShader","name":"EXTVertexShader","qualifiedName":"org.lwjgl.opengl.EXTVertexShader","children":[]},{"key":"EXTVertexWeighting","name":"EXTVertexWeighting","qualifiedName":"org.lwjgl.opengl.EXTVertexWeighting","children":[]},{"key":"EventQueue","name":"EventQueue","qualifiedName":"org.lwjgl.opengl.EventQueue","children":[]},{"key":"FastIntMap","name":"FastIntMap","qualifiedName":"org.lwjgl.opengl.FastIntMap","children":[]},{"key":"GL11","name":"GL11","qualifiedName":"org.lwjgl.opengl.GL11","children":[]},{"key":"GL12","name":"GL12","qualifiedName":"org.lwjgl.opengl.GL12","children":[]},{"key":"GL13","name":"GL13","qualifiedName":"org.lwjgl.opengl.GL13","children":[]},{"key":"GL14","name":"GL14","qualifiedName":"org.lwjgl.opengl.GL14","children":[]},{"key":"GL15","name":"GL15","qualifiedName":"org.lwjgl.opengl.GL15","children":[]},{"key":"GL20","name":"GL20","qualifiedName":"org.lwjgl.opengl.GL20","children":[]},{"key":"GL21","name":"GL21","qualifiedName":"org.lwjgl.opengl.GL21","children":[]},{"key":"GL30","name":"GL30","qualifiedName":"org.lwjgl.opengl.GL30","children":[]},{"key":"GL31","name":"GL31","qualifiedName":"org.lwjgl.opengl.GL31","children":[]},{"key":"GL32","name":"GL32","qualifiedName":"org.lwjgl.opengl.GL32","children":[]},{"key":"GL33","name":"GL33","qualifiedName":"org.lwjgl.opengl.GL33","children":[]},{"key":"GL40","name":"GL40","qualifiedName":"org.lwjgl.opengl.GL40","children":[]},{"key":"GL41","name":"GL41","qualifiedName":"org.lwjgl.opengl.GL41","children":[]},{"key":"GLChecks","name":"GLChecks","qualifiedName":"org.lwjgl.opengl.GLChecks","children":[]},{"key":"GLContext","name":"GLContext","qualifiedName":"org.lwjgl.opengl.GLContext","children":[]},{"key":"GLSync","name":"GLSync","qualifiedName":"org.lwjgl.opengl.GLSync","children":[]},{"key":"GLUConstants","name":"GLUConstants","qualifiedName":"org.lwjgl.opengl.GLUConstants","children":[]},{"key":"GREMEDYStringMarker","name":"GREMEDYStringMarker","qualifiedName":"org.lwjgl.opengl.GREMEDYStringMarker","children":[]},{"key":"GlobalLock","name":"GlobalLock","qualifiedName":"org.lwjgl.opengl.GlobalLock","children":[]},{"key":"HPOcclusionTest","name":"HPOcclusionTest","qualifiedName":"org.lwjgl.opengl.HPOcclusionTest","children":[]},{"key":"IBMRasterposClip","name":"IBMRasterposClip","qualifiedName":"org.lwjgl.opengl.IBMRasterposClip","children":[]},{"key":"InputImplementation","name":"InputImplementation","qualifiedName":"org.lwjgl.opengl.InputImplementation","children":[]},{"key":"KeyboardEventQueue","name":"KeyboardEventQueue","qualifiedName":"org.lwjgl.opengl.KeyboardEventQueue","children":[]},{"key":"LinuxAWTGLCanvasPeerInfo","name":"LinuxAWTGLCanvasPeerInfo","qualifiedName":"org.lwjgl.opengl.LinuxAWTGLCanvasPeerInfo","children":[]},{"key":"LinuxCanvasImplementation","name":"LinuxCanvasImplementation","qualifiedName":"org.lwjgl.opengl.LinuxCanvasImplementation","children":[]},{"key":"LinuxContextAttribs","name":"LinuxContextAttribs","qualifiedName":"org.lwjgl.opengl.LinuxContextAttribs","children":[]},{"key":"LinuxContextImplementation","name":"LinuxContextImplementation","qualifiedName":"org.lwjgl.opengl.LinuxContextImplementation","children":[]},{"key":"LinuxDisplay","name":"LinuxDisplay","qualifiedName":"org.lwjgl.opengl.LinuxDisplay","children":[]},{"key":"LinuxDisplayPeerInfo","name":"LinuxDisplayPeerInfo","qualifiedName":"org.lwjgl.opengl.LinuxDisplayPeerInfo","children":[]},{"key":"LinuxEvent","name":"LinuxEvent","qualifiedName":"org.lwjgl.opengl.LinuxEvent","children":[]},{"key":"LinuxKeyboard","name":"LinuxKeyboard","qualifiedName":"org.lwjgl.opengl.LinuxKeyboard","children":[]},{"key":"LinuxKeycodes","name":"LinuxKeycodes","qualifiedName":"org.lwjgl.opengl.LinuxKeycodes","children":[]},{"key":"LinuxMouse","name":"LinuxMouse","qualifiedName":"org.lwjgl.opengl.LinuxMouse","children":[]},{"key":"LinuxPbufferPeerInfo","name":"LinuxPbufferPeerInfo","qualifiedName":"org.lwjgl.opengl.LinuxPbufferPeerInfo","children":[]},{"key":"LinuxPeerInfo","name":"LinuxPeerInfo","qualifiedName":"org.lwjgl.opengl.LinuxPeerInfo","children":[]},{"key":"MacOSXAWTGLCanvasPeerInfo","name":"MacOSXAWTGLCanvasPeerInfo","qualifiedName":"org.lwjgl.opengl.MacOSXAWTGLCanvasPeerInfo","children":[]},{"key":"MacOSXCanvasImplementation","name":"MacOSXCanvasImplementation","qualifiedName":"org.lwjgl.opengl.MacOSXCanvasImplementation","children":[]},{"key":"MacOSXCanvasListener","name":"MacOSXCanvasListener","qualifiedName":"org.lwjgl.opengl.MacOSXCanvasListener","children":[]},{"key":"MacOSXCanvasPeerInfo","name":"MacOSXCanvasPeerInfo","qualifiedName":"org.lwjgl.opengl.MacOSXCanvasPeerInfo","children":[]},{"key":"MacOSXContextAttribs","name":"MacOSXContextAttribs","qualifiedName":"org.lwjgl.opengl.MacOSXContextAttribs","children":[]},{"key":"MacOSXContextImplementation","name":"MacOSXContextImplementation","qualifiedName":"org.lwjgl.opengl.MacOSXContextImplementation","children":[]},{"key":"MacOSXDisplay","name":"MacOSXDisplay","qualifiedName":"org.lwjgl.opengl.MacOSXDisplay","children":[]},{"key":"MacOSXDisplayPeerInfo","name":"MacOSXDisplayPeerInfo","qualifiedName":"org.lwjgl.opengl.MacOSXDisplayPeerInfo","children":[]},{"key":"MacOSXFrame","name":"MacOSXFrame","qualifiedName":"org.lwjgl.opengl.MacOSXFrame","children":[]},{"key":"MacOSXGLCanvas","name":"MacOSXGLCanvas","qualifiedName":"org.lwjgl.opengl.MacOSXGLCanvas","children":[]},{"key":"MacOSXMouseEventQueue","name":"MacOSXMouseEventQueue","qualifiedName":"org.lwjgl.opengl.MacOSXMouseEventQueue","children":[]},{"key":"MacOSXPbufferPeerInfo","name":"MacOSXPbufferPeerInfo","qualifiedName":"org.lwjgl.opengl.MacOSXPbufferPeerInfo","children":[]},{"key":"MacOSXPeerInfo","name":"MacOSXPeerInfo","qualifiedName":"org.lwjgl.opengl.MacOSXPeerInfo","children":[]},{"key":"MouseEventQueue","name":"MouseEventQueue","qualifiedName":"org.lwjgl.opengl.MouseEventQueue","children":[]},{"key":"NVConditionalRender","name":"NVConditionalRender","qualifiedName":"org.lwjgl.opengl.NVConditionalRender","children":[]},{"key":"NVCopyDepthToColor","name":"NVCopyDepthToColor","qualifiedName":"org.lwjgl.opengl.NVCopyDepthToColor","children":[]},{"key":"NVCopyImage","name":"NVCopyImage","qualifiedName":"org.lwjgl.opengl.NVCopyImage","children":[]},{"key":"NVDepthBufferFloat","name":"NVDepthBufferFloat","qualifiedName":"org.lwjgl.opengl.NVDepthBufferFloat","children":[]},{"key":"NVDepthClamp","name":"NVDepthClamp","qualifiedName":"org.lwjgl.opengl.NVDepthClamp","children":[]},{"key":"NVEvaluators","name":"NVEvaluators","qualifiedName":"org.lwjgl.opengl.NVEvaluators","children":[]},{"key":"NVExplicitMultisample","name":"NVExplicitMultisample","qualifiedName":"org.lwjgl.opengl.NVExplicitMultisample","children":[]},{"key":"NVFence","name":"NVFence","qualifiedName":"org.lwjgl.opengl.NVFence","children":[]},{"key":"NVFloatBuffer","name":"NVFloatBuffer","qualifiedName":"org.lwjgl.opengl.NVFloatBuffer","children":[]},{"key":"NVFogDistance","name":"NVFogDistance","qualifiedName":"org.lwjgl.opengl.NVFogDistance","children":[]},{"key":"NVFragmentProgram","name":"NVFragmentProgram","qualifiedName":"org.lwjgl.opengl.NVFragmentProgram","children":[]},{"key":"NVFragmentProgram2","name":"NVFragmentProgram2","qualifiedName":"org.lwjgl.opengl.NVFragmentProgram2","children":[]},{"key":"NVFramebufferMultisampleCoverage","name":"NVFramebufferMultisampleCoverage","qualifiedName":"org.lwjgl.opengl.NVFramebufferMultisampleCoverage","children":[]},{"key":"NVGeometryProgram4","name":"NVGeometryProgram4","qualifiedName":"org.lwjgl.opengl.NVGeometryProgram4","children":[]},{"key":"NVGpuProgram4","name":"NVGpuProgram4","qualifiedName":"org.lwjgl.opengl.NVGpuProgram4","children":[]},{"key":"NVGpuProgram5","name":"NVGpuProgram5","qualifiedName":"org.lwjgl.opengl.NVGpuProgram5","children":[]},{"key":"NVGpuShader5","name":"NVGpuShader5","qualifiedName":"org.lwjgl.opengl.NVGpuShader5","children":[]},{"key":"NVHalfFloat","name":"NVHalfFloat","qualifiedName":"org.lwjgl.opengl.NVHalfFloat","children":[]},{"key":"NVLightMaxExponent","name":"NVLightMaxExponent","qualifiedName":"org.lwjgl.opengl.NVLightMaxExponent","children":[]},{"key":"NVMultisampleCoverage","name":"NVMultisampleCoverage","qualifiedName":"org.lwjgl.opengl.NVMultisampleCoverage","children":[]},{"key":"NVMultisampleFilterHint","name":"NVMultisampleFilterHint","qualifiedName":"org.lwjgl.opengl.NVMultisampleFilterHint","children":[]},{"key":"NVOcclusionQuery","name":"NVOcclusionQuery","qualifiedName":"org.lwjgl.opengl.NVOcclusionQuery","children":[]},{"key":"NVPackedDepthStencil","name":"NVPackedDepthStencil","qualifiedName":"org.lwjgl.opengl.NVPackedDepthStencil","children":[]},{"key":"NVParameterBufferObject","name":"NVParameterBufferObject","qualifiedName":"org.lwjgl.opengl.NVParameterBufferObject","children":[]},{"key":"NVPixelDataRange","name":"NVPixelDataRange","qualifiedName":"org.lwjgl.opengl.NVPixelDataRange","children":[]},{"key":"NVPointSprite","name":"NVPointSprite","qualifiedName":"org.lwjgl.opengl.NVPointSprite","children":[]},{"key":"NVPrimitiveRestart","name":"NVPrimitiveRestart","qualifiedName":"org.lwjgl.opengl.NVPrimitiveRestart","children":[]},{"key":"NVProgram","name":"NVProgram","qualifiedName":"org.lwjgl.opengl.NVProgram","children":[]},{"key":"NVRegisterCombiners","name":"NVRegisterCombiners","qualifiedName":"org.lwjgl.opengl.NVRegisterCombiners","children":[]},{"key":"NVRegisterCombiners2","name":"NVRegisterCombiners2","qualifiedName":"org.lwjgl.opengl.NVRegisterCombiners2","children":[]},{"key":"NVShaderBufferLoad","name":"NVShaderBufferLoad","qualifiedName":"org.lwjgl.opengl.NVShaderBufferLoad","children":[]},{"key":"NVShaderBufferStore","name":"NVShaderBufferStore","qualifiedName":"org.lwjgl.opengl.NVShaderBufferStore","children":[]},{"key":"NVTessellationProgram5","name":"NVTessellationProgram5","qualifiedName":"org.lwjgl.opengl.NVTessellationProgram5","children":[]},{"key":"NVTexgenReflection","name":"NVTexgenReflection","qualifiedName":"org.lwjgl.opengl.NVTexgenReflection","children":[]},{"key":"NVTextureBarrier","name":"NVTextureBarrier","qualifiedName":"org.lwjgl.opengl.NVTextureBarrier","children":[]},{"key":"NVTextureCompressionVTC","name":"NVTextureCompressionVTC","qualifiedName":"org.lwjgl.opengl.NVTextureCompressionVTC","children":[]},{"key":"NVTextureEnvCombine4","name":"NVTextureEnvCombine4","qualifiedName":"org.lwjgl.opengl.NVTextureEnvCombine4","children":[]},{"key":"NVTextureExpandNormal","name":"NVTextureExpandNormal","qualifiedName":"org.lwjgl.opengl.NVTextureExpandNormal","children":[]},{"key":"NVTextureRectangle","name":"NVTextureRectangle","qualifiedName":"org.lwjgl.opengl.NVTextureRectangle","children":[]},{"key":"NVTextureShader","name":"NVTextureShader","qualifiedName":"org.lwjgl.opengl.NVTextureShader","children":[]},{"key":"NVTextureShader2","name":"NVTextureShader2","qualifiedName":"org.lwjgl.opengl.NVTextureShader2","children":[]},{"key":"NVTextureShader3","name":"NVTextureShader3","qualifiedName":"org.lwjgl.opengl.NVTextureShader3","children":[]},{"key":"NVTransformFeedback","name":"NVTransformFeedback","qualifiedName":"org.lwjgl.opengl.NVTransformFeedback","children":[]},{"key":"NVTransformFeedback2","name":"NVTransformFeedback2","qualifiedName":"org.lwjgl.opengl.NVTransformFeedback2","children":[]},{"key":"NVVertexArrayRange","name":"NVVertexArrayRange","qualifiedName":"org.lwjgl.opengl.NVVertexArrayRange","children":[]},{"key":"NVVertexArrayRange2","name":"NVVertexArrayRange2","qualifiedName":"org.lwjgl.opengl.NVVertexArrayRange2","children":[]},{"key":"NVVertexAttribInteger64bit","name":"NVVertexAttribInteger64bit","qualifiedName":"org.lwjgl.opengl.NVVertexAttribInteger64bit","children":[]},{"key":"NVVertexBufferUnifiedMemory","name":"NVVertexBufferUnifiedMemory","qualifiedName":"org.lwjgl.opengl.NVVertexBufferUnifiedMemory","children":[]},{"key":"NVVertexProgram","name":"NVVertexProgram","qualifiedName":"org.lwjgl.opengl.NVVertexProgram","children":[]},{"key":"NVVertexProgram2Option","name":"NVVertexProgram2Option","qualifiedName":"org.lwjgl.opengl.NVVertexProgram2Option","children":[]},{"key":"NVVertexProgram3","name":"NVVertexProgram3","qualifiedName":"org.lwjgl.opengl.NVVertexProgram3","children":[]},{"key":"NVXGpuMemoryInfo","name":"NVXGpuMemoryInfo","qualifiedName":"org.lwjgl.opengl.NVXGpuMemoryInfo","children":[]},{"key":"OpenGLException","name":"OpenGLException","qualifiedName":"org.lwjgl.opengl.OpenGLException","children":[]},{"key":"Pbuffer","name":"Pbuffer","qualifiedName":"org.lwjgl.opengl.Pbuffer","children":[]},{"key":"PeerInfo","name":"PeerInfo","qualifiedName":"org.lwjgl.opengl.PeerInfo","children":[]},{"key":"PixelFormat","name":"PixelFormat","qualifiedName":"org.lwjgl.opengl.PixelFormat","children":[]},{"key":"References","name":"References","qualifiedName":"org.lwjgl.opengl.References","children":[]},{"key":"ReferencesStack","name":"ReferencesStack","qualifiedName":"org.lwjgl.opengl.ReferencesStack","children":[]},{"key":"RenderTexture","name":"RenderTexture","qualifiedName":"org.lwjgl.opengl.RenderTexture","children":[]},{"key":"SGISGenerateMipmap","name":"SGISGenerateMipmap","qualifiedName":"org.lwjgl.opengl.SGISGenerateMipmap","children":[]},{"key":"SGISTextureLOD","name":"SGISTextureLOD","qualifiedName":"org.lwjgl.opengl.SGISTextureLOD","children":[]},{"key":"SUNSliceAccum","name":"SUNSliceAccum","qualifiedName":"org.lwjgl.opengl.SUNSliceAccum","children":[]},{"key":"SharedDrawable","name":"SharedDrawable","qualifiedName":"org.lwjgl.opengl.SharedDrawable","children":[]},{"key":"StateStack","name":"StateStack","qualifiedName":"org.lwjgl.opengl.StateStack","children":[]},{"key":"StateTracker","name":"StateTracker","qualifiedName":"org.lwjgl.opengl.StateTracker","children":[]},{"key":"Util","name":"Util","qualifiedName":"org.lwjgl.opengl.Util","children":[]},{"key":"WindowsAWTGLCanvasPeerInfo","name":"WindowsAWTGLCanvasPeerInfo","qualifiedName":"org.lwjgl.opengl.WindowsAWTGLCanvasPeerInfo","children":[]},{"key":"WindowsCanvasImplementation","name":"WindowsCanvasImplementation","qualifiedName":"org.lwjgl.opengl.WindowsCanvasImplementation","children":[]},{"key":"WindowsContextAttribs","name":"WindowsContextAttribs","qualifiedName":"org.lwjgl.opengl.WindowsContextAttribs","children":[]},{"key":"WindowsContextImplementation","name":"WindowsContextImplementation","qualifiedName":"org.lwjgl.opengl.WindowsContextImplementation","children":[]},{"key":"WindowsDisplay","name":"WindowsDisplay","qualifiedName":"org.lwjgl.opengl.WindowsDisplay","children":[]},{"key":"WindowsDisplayPeerInfo","name":"WindowsDisplayPeerInfo","qualifiedName":"org.lwjgl.opengl.WindowsDisplayPeerInfo","children":[]},{"key":"WindowsFileVersion","name":"WindowsFileVersion","qualifiedName":"org.lwjgl.opengl.WindowsFileVersion","children":[]},{"key":"WindowsKeyboard","name":"WindowsKeyboard","qualifiedName":"org.lwjgl.opengl.WindowsKeyboard","children":[]},{"key":"WindowsKeycodes","name":"WindowsKeycodes","qualifiedName":"org.lwjgl.opengl.WindowsKeycodes","children":[]},{"key":"WindowsMouse","name":"WindowsMouse","qualifiedName":"org.lwjgl.opengl.WindowsMouse","children":[]},{"key":"WindowsPbufferPeerInfo","name":"WindowsPbufferPeerInfo","qualifiedName":"org.lwjgl.opengl.WindowsPbufferPeerInfo","children":[]},{"key":"WindowsPeerInfo","name":"WindowsPeerInfo","qualifiedName":"org.lwjgl.opengl.WindowsPeerInfo","children":[]},{"key":"WindowsRegistry","name":"WindowsRegistry","qualifiedName":"org.lwjgl.opengl.WindowsRegistry","children":[]},{"key":"XRandR","name":"XRandR","qualifiedName":"org.lwjgl.opengl.XRandR","children":[]}]},{"key":"test","name":"","qualifiedName":"","children":[{"key":"DisplayTest","name":"DisplayTest","qualifiedName":"org.lwjgl.test.DisplayTest","children":[]},{"key":"NativeTest","name":"NativeTest","qualifiedName":"org.lwjgl.test.NativeTest","children":[]},{"key":"SysTest","name":"SysTest","qualifiedName":"org.lwjgl.test.SysTest","children":[]},{"key":"WaveDataTest","name":"WaveDataTest","qualifiedName":"org.lwjgl.test.WaveDataTest","children":[]},{"key":"WindowCreationTest","name":"WindowCreationTest","qualifiedName":"org.lwjgl.test.WindowCreationTest","children":[]},{"key":"applet","name":"","qualifiedName":"","children":[{"key":"AppletLoaderTest","name":"AppletLoaderTest","qualifiedName":"org.lwjgl.test.applet.AppletLoaderTest","children":[]},{"key":"ControllersTest","name":"ControllersTest","qualifiedName":"org.lwjgl.test.applet.ControllersTest","children":[]},{"key":"GearsApplet","name":"GearsApplet","qualifiedName":"org.lwjgl.test.applet.GearsApplet","children":[]},{"key":"OpenAL","name":"OpenAL","qualifiedName":"org.lwjgl.test.applet.OpenAL","children":[]},{"key":"OpenGL","name":"OpenGL","qualifiedName":"org.lwjgl.test.applet.OpenGL","children":[]},{"key":"Speed","name":"Speed","qualifiedName":"org.lwjgl.test.applet.Speed","children":[]},{"key":"Test","name":"Test","qualifiedName":"org.lwjgl.test.applet.Test","children":[]}]},{"key":"glu","name":"","qualifiedName":"","children":[{"key":"tessellation","name":"","qualifiedName":"","children":[{"key":"TessCallback","name":"TessCallback","qualifiedName":"org.lwjgl.test.glu.tessellation.TessCallback","children":[]},{"key":"TessellationTest","name":"TessellationTest","qualifiedName":"org.lwjgl.test.glu.tessellation.TessellationTest","children":[]},{"key":"VertexData","name":"VertexData","qualifiedName":"org.lwjgl.test.glu.tessellation.VertexData","children":[]}]}]},{"key":"input","name":"","qualifiedName":"","children":[{"key":"HWCursorTest","name":"HWCursorTest","qualifiedName":"org.lwjgl.test.input.HWCursorTest","children":[]},{"key":"KeyboardTest","name":"KeyboardTest","qualifiedName":"org.lwjgl.test.input.KeyboardTest","children":[]},{"key":"MouseCreationTest","name":"MouseCreationTest","qualifiedName":"org.lwjgl.test.input.MouseCreationTest","children":[]},{"key":"MouseTest","name":"MouseTest","qualifiedName":"org.lwjgl.test.input.MouseTest","children":[]},{"key":"TestControllers","name":"TestControllers","qualifiedName":"org.lwjgl.test.input.TestControllers","children":[]}]},{"key":"openal","name":"","qualifiedName":"","children":[{"key":"ALCCaptureTest","name":"ALCCaptureTest","qualifiedName":"org.lwjgl.test.openal.ALCCaptureTest","children":[]},{"key":"ALCTest","name":"ALCTest","qualifiedName":"org.lwjgl.test.openal.ALCTest","children":[]},{"key":"BasicTest","name":"BasicTest","qualifiedName":"org.lwjgl.test.openal.BasicTest","children":[]},{"key":"EFX10Test","name":"EFX10Test","qualifiedName":"org.lwjgl.test.openal.EFX10Test","children":[]},{"key":"MovingSoundTest","name":"MovingSoundTest","qualifiedName":"org.lwjgl.test.openal.MovingSoundTest","children":[]},{"key":"OpenALCreationTest","name":"OpenALCreationTest","qualifiedName":"org.lwjgl.test.openal.OpenALCreationTest","children":[]},{"key":"OpenALInfo","name":"OpenALInfo","qualifiedName":"org.lwjgl.test.openal.OpenALInfo","children":[]},{"key":"PlayTest","name":"PlayTest","qualifiedName":"org.lwjgl.test.openal.PlayTest","children":[]},{"key":"PlayTestMemory","name":"PlayTestMemory","qualifiedName":"org.lwjgl.test.openal.PlayTestMemory","children":[]},{"key":"PositionTest","name":"PositionTest","qualifiedName":"org.lwjgl.test.openal.PositionTest","children":[]},{"key":"SourceLimitTest","name":"SourceLimitTest","qualifiedName":"org.lwjgl.test.openal.SourceLimitTest","children":[]},{"key":"StressTest","name":"StressTest","qualifiedName":"org.lwjgl.test.openal.StressTest","children":[]}]},{"key":"opencl","name":"","qualifiedName":"","children":[{"key":"HelloOpenCL","name":"HelloOpenCL","qualifiedName":"org.lwjgl.test.opencl.HelloOpenCL","children":[]},{"key":"gl","name":"","qualifiedName":"","children":[{"key":"DemoFractal","name":"DemoFractal","qualifiedName":"org.lwjgl.test.opencl.gl.DemoFractal","children":[]}]}]},{"key":"opengl","name":"","qualifiedName":"","children":[{"key":"FullScreenWindowedTest","name":"FullScreenWindowedTest","qualifiedName":"org.lwjgl.test.opengl.FullScreenWindowedTest","children":[]},{"key":"Gears","name":"Gears","qualifiedName":"org.lwjgl.test.opengl.Gears","children":[]},{"key":"PbufferTest","name":"PbufferTest","qualifiedName":"org.lwjgl.test.opengl.PbufferTest","children":[]},{"key":"SyncTest","name":"SyncTest","qualifiedName":"org.lwjgl.test.opengl.SyncTest","children":[]},{"key":"VBOIndexTest","name":"VBOIndexTest","qualifiedName":"org.lwjgl.test.opengl.VBOIndexTest","children":[]},{"key":"VBOTest","name":"VBOTest","qualifiedName":"org.lwjgl.test.opengl.VBOTest","children":[]},{"key":"VersionTest","name":"VersionTest","qualifiedName":"org.lwjgl.test.opengl.VersionTest","children":[]},{"key":"awt","name":"","qualifiedName":"","children":[{"key":"AWTGears","name":"AWTGears","qualifiedName":"org.lwjgl.test.opengl.awt.AWTGears","children":[]},{"key":"AWTGearsCanvas","name":"AWTGearsCanvas","qualifiedName":"org.lwjgl.test.opengl.awt.AWTGearsCanvas","children":[]},{"key":"AWTTest","name":"AWTTest","qualifiedName":"org.lwjgl.test.opengl.awt.AWTTest","children":[]},{"key":"DemoBox","name":"DemoBox","qualifiedName":"org.lwjgl.test.opengl.awt.DemoBox","children":[]},{"key":"DisplayParentTest","name":"DisplayParentTest","qualifiedName":"org.lwjgl.test.opengl.awt.DisplayParentTest","children":[]}]},{"key":"multithread","name":"","qualifiedName":"","children":[{"key":"BackgroundLoadTest","name":"BackgroundLoadTest","qualifiedName":"org.lwjgl.test.opengl.multithread.BackgroundLoadTest","children":[]},{"key":"BackgroundLoader","name":"BackgroundLoader","qualifiedName":"org.lwjgl.test.opengl.multithread.BackgroundLoader","children":[]}]},{"key":"pbuffers","name":"","qualifiedName":"","children":[{"key":"PbufferTest","name":"PbufferTest","qualifiedName":"org.lwjgl.test.opengl.pbuffers.PbufferTest","children":[]},{"key":"TextureRenderer","name":"TextureRenderer","qualifiedName":"org.lwjgl.test.opengl.pbuffers.TextureRenderer","children":[]},{"key":"UniqueRenderer","name":"UniqueRenderer","qualifiedName":"org.lwjgl.test.opengl.pbuffers.UniqueRenderer","children":[]},{"key":"UniqueRendererRTT","name":"UniqueRendererRTT","qualifiedName":"org.lwjgl.test.opengl.pbuffers.UniqueRendererRTT","children":[]}]},{"key":"shaders","name":"","qualifiedName":"","children":[{"key":"Shader","name":"Shader","qualifiedName":"org.lwjgl.test.opengl.shaders.Shader","children":[]},{"key":"ShaderFP","name":"ShaderFP","qualifiedName":"org.lwjgl.test.opengl.shaders.ShaderFP","children":[]},{"key":"ShaderFSH","name":"ShaderFSH","qualifiedName":"org.lwjgl.test.opengl.shaders.ShaderFSH","children":[]},{"key":"ShaderUNI","name":"ShaderUNI","qualifiedName":"org.lwjgl.test.opengl.shaders.ShaderUNI","children":[]},{"key":"ShaderVP","name":"ShaderVP","qualifiedName":"org.lwjgl.test.opengl.shaders.ShaderVP","children":[]},{"key":"ShaderVSH","name":"ShaderVSH","qualifiedName":"org.lwjgl.test.opengl.shaders.ShaderVSH","children":[]},{"key":"ShadersTest","name":"ShadersTest","qualifiedName":"org.lwjgl.test.opengl.shaders.ShadersTest","children":[]}]}]}]},{"key":"util","name":"","qualifiedName":"","children":[{"key":"Color","name":"Color","qualifiedName":"org.lwjgl.util.Color","children":[]},{"key":"Dimension","name":"Dimension","qualifiedName":"org.lwjgl.util.Dimension","children":[]},{"key":"Display","name":"Display","qualifiedName":"org.lwjgl.util.Display","children":[]},{"key":"Point","name":"Point","qualifiedName":"org.lwjgl.util.Point","children":[]},{"key":"ReadableColor","name":"ReadableColor","qualifiedName":"org.lwjgl.util.ReadableColor","children":[]},{"key":"ReadableDimension","name":"ReadableDimension","qualifiedName":"org.lwjgl.util.ReadableDimension","children":[]},{"key":"ReadablePoint","name":"ReadablePoint","qualifiedName":"org.lwjgl.util.ReadablePoint","children":[]},{"key":"ReadableRectangle","name":"ReadableRectangle","qualifiedName":"org.lwjgl.util.ReadableRectangle","children":[]},{"key":"Rectangle","name":"Rectangle","qualifiedName":"org.lwjgl.util.Rectangle","children":[]},{"key":"Renderable","name":"Renderable","qualifiedName":"org.lwjgl.util.Renderable","children":[]},{"key":"Timer","name":"Timer","qualifiedName":"org.lwjgl.util.Timer","children":[]},{"key":"WaveData","name":"WaveData","qualifiedName":"org.lwjgl.util.WaveData","children":[]},{"key":"WritableColor","name":"WritableColor","qualifiedName":"org.lwjgl.util.WritableColor","children":[]},{"key":"WritableDimension","name":"WritableDimension","qualifiedName":"org.lwjgl.util.WritableDimension","children":[]},{"key":"WritablePoint","name":"WritablePoint","qualifiedName":"org.lwjgl.util.WritablePoint","children":[]},{"key":"WritableRectangle","name":"WritableRectangle","qualifiedName":"org.lwjgl.util.WritableRectangle","children":[]},{"key":"XPMFile","name":"XPMFile","qualifiedName":"org.lwjgl.util.XPMFile","children":[]},{"key":"applet","name":"","qualifiedName":"","children":[{"key":"AppletLoader","name":"AppletLoader","qualifiedName":"org.lwjgl.util.applet.AppletLoader","children":[]}]},{"key":"glu","name":"","qualifiedName":"","children":[{"key":"Cylinder","name":"Cylinder","qualifiedName":"org.lwjgl.util.glu.Cylinder","children":[]},{"key":"Disk","name":"Disk","qualifiedName":"org.lwjgl.util.glu.Disk","children":[]},{"key":"GLU","name":"GLU","qualifiedName":"org.lwjgl.util.glu.GLU","children":[]},{"key":"GLUtessellator","name":"GLUtessellator","qualifiedName":"org.lwjgl.util.glu.GLUtessellator","children":[]},{"key":"GLUtessellatorCallback","name":"GLUtessellatorCallback","qualifiedName":"org.lwjgl.util.glu.GLUtessellatorCallback","children":[]},{"key":"GLUtessellatorCallbackAdapter","name":"GLUtessellatorCallbackAdapter","qualifiedName":"org.lwjgl.util.glu.GLUtessellatorCallbackAdapter","children":[]},{"key":"MipMap","name":"MipMap","qualifiedName":"org.lwjgl.util.glu.MipMap","children":[]},{"key":"PartialDisk","name":"PartialDisk","qualifiedName":"org.lwjgl.util.glu.PartialDisk","children":[]},{"key":"PixelStoreState","name":"PixelStoreState","qualifiedName":"org.lwjgl.util.glu.PixelStoreState","children":[]},{"key":"Project","name":"Project","qualifiedName":"org.lwjgl.util.glu.Project","children":[]},{"key":"Quadric","name":"Quadric","qualifiedName":"org.lwjgl.util.glu.Quadric","children":[]},{"key":"Registry","name":"Registry","qualifiedName":"org.lwjgl.util.glu.Registry","children":[]},{"key":"Sphere","name":"Sphere","qualifiedName":"org.lwjgl.util.glu.Sphere","children":[]},{"key":"Util","name":"Util","qualifiedName":"org.lwjgl.util.glu.Util","children":[]},{"key":"tessellation","name":"","qualifiedName":"","children":[{"key":"ActiveRegion","name":"ActiveRegion","qualifiedName":"org.lwjgl.util.glu.tessellation.ActiveRegion","children":[]},{"key":"CachedVertex","name":"CachedVertex","qualifiedName":"org.lwjgl.util.glu.tessellation.CachedVertex","children":[]},{"key":"Dict","name":"Dict","qualifiedName":"org.lwjgl.util.glu.tessellation.Dict","children":[]},{"key":"DictNode","name":"DictNode","qualifiedName":"org.lwjgl.util.glu.tessellation.DictNode","children":[]},{"key":"GLUface","name":"GLUface","qualifiedName":"org.lwjgl.util.glu.tessellation.GLUface","children":[]},{"key":"GLUhalfEdge","name":"GLUhalfEdge","qualifiedName":"org.lwjgl.util.glu.tessellation.GLUhalfEdge","children":[]},{"key":"GLUmesh","name":"GLUmesh","qualifiedName":"org.lwjgl.util.glu.tessellation.GLUmesh","children":[]},{"key":"GLUtessellatorImpl","name":"GLUtessellatorImpl","qualifiedName":"org.lwjgl.util.glu.tessellation.GLUtessellatorImpl","children":[]},{"key":"GLUvertex","name":"GLUvertex","qualifiedName":"org.lwjgl.util.glu.tessellation.GLUvertex","children":[]},{"key":"Geom","name":"Geom","qualifiedName":"org.lwjgl.util.glu.tessellation.Geom","children":[]},{"key":"Mesh","name":"Mesh","qualifiedName":"org.lwjgl.util.glu.tessellation.Mesh","children":[]},{"key":"Normal","name":"Normal","qualifiedName":"org.lwjgl.util.glu.tessellation.Normal","children":[]},{"key":"PriorityQ","name":"PriorityQ","qualifiedName":"org.lwjgl.util.glu.tessellation.PriorityQ","children":[]},{"key":"PriorityQHeap","name":"PriorityQHeap","qualifiedName":"org.lwjgl.util.glu.tessellation.PriorityQHeap","children":[]},{"key":"PriorityQSort","name":"PriorityQSort","qualifiedName":"org.lwjgl.util.glu.tessellation.PriorityQSort","children":[]},{"key":"Render","name":"Render","qualifiedName":"org.lwjgl.util.glu.tessellation.Render","children":[]},{"key":"Sweep","name":"Sweep","qualifiedName":"org.lwjgl.util.glu.tessellation.Sweep","children":[]},{"key":"TessMono","name":"TessMono","qualifiedName":"org.lwjgl.util.glu.tessellation.TessMono","children":[]},{"key":"TessState","name":"TessState","qualifiedName":"org.lwjgl.util.glu.tessellation.TessState","children":[]}]}]},{"key":"input","name":"","qualifiedName":"","children":[{"key":"ControllerAdapter","name":"ControllerAdapter","qualifiedName":"org.lwjgl.util.input.ControllerAdapter","children":[]}]},{"key":"jinput","name":"","qualifiedName":"","children":[{"key":"KeyMap","name":"KeyMap","qualifiedName":"org.lwjgl.util.jinput.KeyMap","children":[]},{"key":"LWJGLEnvironmentPlugin","name":"LWJGLEnvironmentPlugin","qualifiedName":"org.lwjgl.util.jinput.LWJGLEnvironmentPlugin","children":[]},{"key":"LWJGLKeyboard","name":"LWJGLKeyboard","qualifiedName":"org.lwjgl.util.jinput.LWJGLKeyboard","children":[]},{"key":"LWJGLMouse","name":"LWJGLMouse","qualifiedName":"org.lwjgl.util.jinput.LWJGLMouse","children":[]}]},{"key":"vector","name":"","qualifiedName":"","children":[{"key":"Matrix","name":"Matrix","qualifiedName":"org.lwjgl.util.vector.Matrix","children":[]},{"key":"Matrix2f","name":"Matrix2f","qualifiedName":"org.lwjgl.util.vector.Matrix2f","children":[]},{"key":"Matrix3f","name":"Matrix3f","qualifiedName":"org.lwjgl.util.vector.Matrix3f","children":[]},{"key":"Matrix4f","name":"Matrix4f","qualifiedName":"org.lwjgl.util.vector.Matrix4f","children":[]},{"key":"Quaternion","name":"Quaternion","qualifiedName":"org.lwjgl.util.vector.Quaternion","children":[]},{"key":"ReadableVector","name":"ReadableVector","qualifiedName":"org.lwjgl.util.vector.ReadableVector","children":[]},{"key":"ReadableVector2f","name":"ReadableVector2f","qualifiedName":"org.lwjgl.util.vector.ReadableVector2f","children":[]},{"key":"ReadableVector3f","name":"ReadableVector3f","qualifiedName":"org.lwjgl.util.vector.ReadableVector3f","children":[]},{"key":"ReadableVector4f","name":"ReadableVector4f","qualifiedName":"org.lwjgl.util.vector.ReadableVector4f","children":[]},{"key":"Vector","name":"Vector","qualifiedName":"org.lwjgl.util.vector.Vector","children":[]},{"key":"Vector2f","name":"Vector2f","qualifiedName":"org.lwjgl.util.vector.Vector2f","children":[]},{"key":"Vector3f","name":"Vector3f","qualifiedName":"org.lwjgl.util.vector.Vector3f","children":[]},{"key":"Vector4f","name":"Vector4f","qualifiedName":"org.lwjgl.util.vector.Vector4f","children":[]},{"key":"WritableVector2f","name":"WritableVector2f","qualifiedName":"org.lwjgl.util.vector.WritableVector2f","children":[]},{"key":"WritableVector3f","name":"WritableVector3f","qualifiedName":"org.lwjgl.util.vector.WritableVector3f","children":[]},{"key":"WritableVector4f","name":"WritableVector4f","qualifiedName":"org.lwjgl.util.vector.WritableVector4f","children":[]}]}]}]}]}]}}